odoo10_addon_account_invoice_partner-10.0.1.0.0-py2.7-nspkg.pth
odoo/addons/account_invoice_partner/README.rst
odoo/addons/account_invoice_partner/__init__.py
odoo/addons/account_invoice_partner/__manifest__.py
odoo/addons/account_invoice_partner/i18n/es.po
odoo/addons/account_invoice_partner/i18n/fr.po
odoo/addons/account_invoice_partner/i18n/it.po
odoo/addons/account_invoice_partner/i18n/nl.po
odoo/addons/account_invoice_partner/i18n/pt_BR.po
odoo/addons/account_invoice_partner/i18n/sl.po
odoo/addons/account_invoice_partner/i18n/zh_CN.po
odoo/addons/account_invoice_partner/models/__init__.py
odoo/addons/account_invoice_partner/models/account_invoice.py
odoo/addons/account_invoice_partner/tests/__init__.py
odoo/addons/account_invoice_partner/tests/test_account_invoice_partner.py
odoo10_addon_account_invoice_partner-10.0.1.0.0.dist-info/DESCRIPTION.rst
odoo10_addon_account_invoice_partner-10.0.1.0.0.dist-info/METADATA
odoo10_addon_account_invoice_partner-10.0.1.0.0.dist-info/RECORD
odoo10_addon_account_invoice_partner-10.0.1.0.0.dist-info/WHEEL
odoo10_addon_account_invoice_partner-10.0.1.0.0.dist-info/metadata.json
odoo10_addon_account_invoice_partner-10.0.1.0.0.dist-info/namespace_packages.txt
odoo10_addon_account_invoice_partner-10.0.1.0.0.dist-info/top_level.txt
